echoAI/__init__.py
echoAI/Activation/__init__.py
echoAI/Activation/Keras/__init__.py
echoAI/Activation/Keras/custom_activations.py
echoAI/Activation/TF_Keras/__init__.py
echoAI/Activation/TF_Keras/custom_activation.py
echoAI/Activation/Torch/__init__.py
echoAI/Activation/Torch/apl.py
echoAI/Activation/Torch/aria2.py
echoAI/Activation/Torch/bent_id.py
echoAI/Activation/Torch/beta_mish.py
echoAI/Activation/Torch/brelu.py
echoAI/Activation/Torch/elish.py
echoAI/Activation/Torch/eswish.py
echoAI/Activation/Torch/fts.py
echoAI/Activation/Torch/functional.py
echoAI/Activation/Torch/hard_elish.py
echoAI/Activation/Torch/isrlu.py
echoAI/Activation/Torch/isru.py
echoAI/Activation/Torch/maxout.py
echoAI/Activation/Torch/mila.py
echoAI/Activation/Torch/mish.py
echoAI/Activation/Torch/silu.py
echoAI/Activation/Torch/sine_relu.py
echoAI/Activation/Torch/soft_clipping.py
echoAI/Activation/Torch/soft_exponential.py
echoAI/Activation/Torch/sqnl.py
echoAI/Activation/Torch/srelu.py
echoAI/Activation/Torch/swish.py
echoAI/Activation/Torch/weightedTanh.py
echoAI-0.1.3.dist-info/LICENSE
echoAI-0.1.3.dist-info/METADATA
echoAI-0.1.3.dist-info/WHEEL
echoAI-0.1.3.dist-info/top_level.txt
echoAI-0.1.3.dist-info/RECORD
