Metadata-Version: 2.1
Name: echoAI
Version: 0.1.3
Summary: Python package containing all custom and SOTA mathematical backend algorithms used in Machine Learning.
Home-page: https://github.com/digantamisra98/Echo
Author: Diganta Misra and Aleksandra Deis
Author-email: mishradiganta91@gmail.com
License: UNKNOWN
Download-URL: https://github.com/digantamisra98/Echo/archive/0.1.1.tar.gz
Keywords: machine learning,deep learning,algorithms,mathematics
Platform: UNKNOWN
